brisque/__init__.py
brisque/brisque.py
brisque/models/__init__.py
brisque/models/normalize.pickle
brisque/models/svm.txt
brisque/tests/__init__.py
brisque/tests/test_brisque.py
brisque_opencv-0.0.17.dist-info/LICENSE
brisque_opencv-0.0.17.dist-info/METADATA
brisque_opencv-0.0.17.dist-info/WHEEL
brisque_opencv-0.0.17.dist-info/top_level.txt
brisque_opencv-0.0.17.dist-info/RECORD
