Metadata-Version: 2.1
Name: brisque-opencv
Version: 0.0.17
Summary: Image Quality
Home-page: https://github.com/rehanguha/brisque
Author: Rehan Guha
Author-email: rehanguha29@gmail.com
License: mit
Keywords: quality,svm,image,maths
Classifier: Operating System :: OS Independent
Classifier: License :: OSI Approved :: MIT License
Classifier: Natural Language :: English
Classifier: Programming Language :: Python
Classifier: Topic :: Software Development :: Libraries :: Python Modules
Classifier: Topic :: Scientific/Engineering
Classifier: Intended Audience :: Developers
Requires-Python: >=2.7
License-File: LICENSE
Requires-Dist: numpy
Requires-Dist: scikit-image
Requires-Dist: scipy
Requires-Dist: libsvm-official
Provides-Extra: opencv-contrib-python
Requires-Dist: opencv-contrib-python ; extra == 'opencv-contrib-python'
Provides-Extra: opencv-contrib-python-headless
Requires-Dist: opencv-contrib-python-headless ; extra == 'opencv-contrib-python-headless'
Provides-Extra: opencv-python
Requires-Dist: opencv-python ; extra == 'opencv-python'
Provides-Extra: opencv-python-headless
Requires-Dist: opencv-python-headless ; extra == 'opencv-python-headless'
